clusteredtransforms/__about__.py
clusteredtransforms/__init__.py
clusteredtransforms/scale_clustering/__init__.py
clusteredtransforms/scale_clustering/_cluster.py
clusteredtransforms/scale_clustering/_functions.py
clusteredtransforms/scale_clustering/_transform.py
clusteredtransforms-0.0.3.dist-info/METADATA
clusteredtransforms-0.0.3.dist-info/WHEEL
clusteredtransforms-0.0.3.dist-info/licenses/LICENSE
clusteredtransforms-0.0.3.dist-info/RECORD
