Metadata-Version: 2.1
Name: clusteredtransforms
Version: 0.0.3
Summary: Cluster-based spatial transforms.
Project-URL: Documentation, https://github.com/mgczacki/clusteredtransforms#readme
Project-URL: Issues, https://github.com/mgczacki/clusteredtransforms/issues
Project-URL: Source, https://github.com/mgczacki/clusteredtransforms
Author-email: Mario Garrido <mario.garrido@nyu.edu>
License-File: LICENSE
Classifier: Development Status :: 4 - Beta
Classifier: Programming Language :: Python
Classifier: Programming Language :: Python :: 3.7
Classifier: Programming Language :: Python :: 3.8
Classifier: Programming Language :: Python :: 3.9
Classifier: Programming Language :: Python :: 3.10
Classifier: Programming Language :: Python :: 3.11
Classifier: Programming Language :: Python :: Implementation :: CPython
Classifier: Programming Language :: Python :: Implementation :: PyPy
Requires-Python: >=3.7
Requires-Dist: numpy
Requires-Dist: scikit-learn
